aioprogress/__init__.py
aioprogress/downloader.py
aioprogress/events.py
aioprogress/fetch_info.py
aioprogress/progress.py
aioprogress/requirements.txt
aioprogress/speedtest.py
aioprogress/utils.py
aioprogress-0.2.2.3.dist-info/licenses/LICENSE
aioprogress-0.2.2.3.dist-info/WHEEL
aioprogress-0.2.2.3.dist-info/METADATA
aioprogress-0.2.2.3.dist-info/RECORD
