Metadata-Version: 2.4
Name: aioprogress
Version: 0.2.2.3
Summary: A high-performance, flexible async file downloader built with aiohttp.
Author-email: Javad Dalirani <jdalirani82@gmail.com>
Requires-Python: >=3.7
Classifier: Programming Language :: Python :: 3
Classifier: Operating System :: OS Independent
License-File: LICENSE
Requires-Dist: aiohttp
Requires-Dist: aiofiles
Project-URL: Homepage, https://github.com/javad2nd/aioprogress
